{"nodes": [{"id": "c_users_bjork_dev_bussruta_readme_md", "label": "README.md", "file_type": "document", "source_file": "C:\\Users\\bjork\\dev\\bussruta\\README.md", "source_location": "L1"}, {"id": "bussruta_readme_bussruta_app", "label": "bussruta_app", "file_type": "document", "source_file": "C:\\Users\\bjork\\dev\\bussruta\\README.md", "source_location": "L1"}, {"id": "bussruta_readme_getting_started", "label": "Getting Started", "file_type": "document", "source_file": "C:\\Users\\bjork\\dev\\bussruta\\README.md", "source_location": "L5"}], "edges": [{"source": "c_users_bjork_dev_bussruta_readme_md", "target": "bussruta_readme_bussruta_app", "relation": "contains", "confidence": "EXTRACTED", "source_file": "C:\\Users\\bjork\\dev\\bussruta\\README.md", "source_location": "L1", "weight": 1.0}, {"source": "bussruta_readme_bussruta_app", "target": "bussruta_readme_getting_started", "relation": "contains", "confidence": "EXTRACTED", "source_file": "C:\\Users\\bjork\\dev\\bussruta\\README.md", "source_location": "L5", "weight": 1.0}], "input_tokens": 0, "output_tokens": 0}